spinner/__init__.py
spinner/__main__.py
spinner/app.py
spinner/schema.py
spinner/cli/__init__.py
spinner/cli/main.py
spinner/cli/util.py
spinner/exporter/__init__.py
spinner/exporter/exporter.py
spinner/exporter/reporter.ipynb
spinner/runner/__init__.py
spinner/runner/instance_runner.py
spinner/runner/progress.py
spinner/runner/utilities.py
spinner-1.2.0.data/data/spinner/reporter.ipynb
spinner-1.2.0.dist-info/licenses/LICENSE
spinner-1.2.0.dist-info/METADATA
spinner-1.2.0.dist-info/WHEEL
spinner-1.2.0.dist-info/entry_points.txt
spinner-1.2.0.dist-info/top_level.txt
spinner-1.2.0.dist-info/RECORD
